{
  "jobs": [
    {
      "title": "JOB LETTER2",
      "description": "first desc2",
      "skills": [
        "TEST",
        "pest"
      ],
      "status": "draft",
      "id": "4dc6"
    },
    {
      "id": "a579",
      "description": "dog is a 'good' friend",
      "status": "draft",
      "title": "JOB DOG",
      "skills": []
    },
    {
      "id": "1559",
      "description": "CATS are FuNNy!",
      "status": "draft",
      "title": "JOB CAT",
      "skills": []
    },
    {
      "id": "15555",
      "description": "Very funny.",
      "status": "draft",
      "title": "FUN GUN",
      "skills": []
    },
    {
      "id": "2222",
      "description": "DESCription",
      "status": "draft",
      "title": "Lower case",
      "skills": []
    },
    {
      "id": "1111",
      "description": "Device",
      "status": "draft",
      "title": "Mount",
      "skills": []
    },
    {
      "id": "6da3",
      "title": "TOMA",
      "description": "TOMA",
      "skills": [],
      "status": "draft"
    },
    {
      "id": "741b",
      "title": "asdadd",
      "description": "asdad",
      "skills": [
        "asdsa"
      ],
      "status": "draft"
    }
  ],
  "invoices": [
    {
      "id": "5717",
      "amount": 220,
      "dueDate": "2024-08-31T16:14:07.705Z",
      "jobAdId": "4dc6",
      "jobId": "4dc6"
    },
    {
      "id": "5718",
      "amount": 220,
      "dueDate": "2024-08-31T16:14:07.705Z",
      "jobAdId": "4dc6",
      "jobId": "4dc6"
    },
    {
      "id": "5719",
      "amount": 220,
      "dueDate": "2024-08-31T16:14:07.705Z",
      "jobAdId": "1559",
      "jobId": "1559"
    }
  ]
}